pytorchfwd/__init__.py
pytorchfwd/__main__.py
pytorchfwd/freq_math.py
pytorchfwd/fwd.py
pytorchfwd/utils.py
pytorchfwd/version.py
pytorchfwd-1.0.1.dist-info/licenses/LICENSE
pytorchfwd-1.0.1.dist-info/METADATA
pytorchfwd-1.0.1.dist-info/WHEEL
pytorchfwd-1.0.1.dist-info/top_level.txt
pytorchfwd-1.0.1.dist-info/RECORD
