Metadata-Version: 2.4
Name: pytorchfwd
Version: 1.0.1
Summary: Compute frecet wavelet distances
Home-page: https://github.com/BonnBytes/PyTorch-FWD
Download-URL: https://github.com/BonnBytes/PyTorch-FWD/releases
Author: Lokesh Veeramacheneni
Author-email: lokeshveeramacheneni27@gmail.com
Maintainer: Lokesh Veeramacheneni
Maintainer-email: lokeshveeramacheneni27@gmail.com
License: Apache-2.0 license
Project-URL: Bug Tracker, https://github.com/BonnBytes/PyTorch-FWD/issues
Project-URL: Source Code, https://github.com/BonnBytes/PyTorch-FWD
Keywords: Wavelets,Wavelet Transform,Fast Wavelet Transform,PyTorch,Generative Learning,FID,Frechet Inception Distance
Classifier: Development Status :: 4 - Beta
Classifier: Environment :: Console
Classifier: Intended Audience :: Science/Research
Classifier: Operating System :: OS Independent
Classifier: Programming Language :: Python
Classifier: Programming Language :: Python :: 3 :: Only
Classifier: Programming Language :: Python :: 3.11
Classifier: Topic :: Scientific/Engineering :: Artificial Intelligence
Requires-Python: >=3.9
License-File: LICENSE
Requires-Dist: pillow
Requires-Dist: matplotlib
Requires-Dist: scipy==1.11.1
Requires-Dist: numpy
Requires-Dist: scikit-learn
Requires-Dist: torch
Requires-Dist: torchvision
Requires-Dist: PyWavelets
Requires-Dist: ptwt==0.1.8
Requires-Dist: tqdm
Dynamic: download-url
Dynamic: license-file
